exchangerates/__init__.py
exchangerates/get_rates.py
exchangerates/util.py
exchangerates-0.3.1.dist-info/LICENSE
exchangerates-0.3.1.dist-info/METADATA
exchangerates-0.3.1.dist-info/WHEEL
exchangerates-0.3.1.dist-info/namespace_packages.txt
exchangerates-0.3.1.dist-info/top_level.txt
exchangerates-0.3.1.dist-info/RECORD
