Metadata-Version: 2.1
Name: exchangerates
Version: 0.3.1
Summary: A module to make it easier to handle historical exchange rates
Home-page: http://github.com/markbrough/exchangerates
Author: Mark Brough
Author-email: mark@brough.io
License: MIT
Platform: UNKNOWN
Classifier: Intended Audience :: Developers
Classifier: License :: OSI Approved :: MIT License
Classifier: Operating System :: OS Independent
Classifier: Programming Language :: Python :: 3.6
Requires-Dist: lxml (==4.4.0)
Requires-Dist: requests (==2.22.0)
Requires-Dist: six (==1.12.0)
